sliding_window_counter/__init__.py
sliding_window_counter/_version.py
sliding_window_counter/py.typed
sliding_window_counter-0.0.1.dist-info/LICENCE
sliding_window_counter-0.0.1.dist-info/METADATA
sliding_window_counter-0.0.1.dist-info/NOTICE
sliding_window_counter-0.0.1.dist-info/WHEEL
sliding_window_counter-0.0.1.dist-info/top_level.txt
sliding_window_counter-0.0.1.dist-info/RECORD
