Metadata-Version: 2.1
Name: sliding-window-counter
Version: 0.0.1
Summary: Counter with a time based sliding window
Author-email: Nicholas Hairs <info@nicholashairs.com>
License: MIT License
Classifier: Programming Language :: Python :: 3 :: Only
Classifier: Programming Language :: Python :: 3.8
Classifier: Programming Language :: Python :: 3.9
Classifier: Programming Language :: Python :: 3.10
Classifier: Programming Language :: Python :: 3.11
Classifier: Programming Language :: Python :: 3.12
Classifier: Development Status :: 3 - Alpha
Classifier: Intended Audience :: Developers
Classifier: Typing :: Typed
Classifier: License :: OSI Approved :: MIT License
Requires-Python: >=3.8
License-File: LICENCE
License-File: NOTICE
Provides-Extra: dev
Requires-Dist: freezegun ; extra == 'dev'
Requires-Dist: validate-pyproject[all] ; extra == 'dev'
Requires-Dist: black ; extra == 'dev'
Requires-Dist: pylint ; extra == 'dev'
Requires-Dist: mypy ; extra == 'dev'
Requires-Dist: pytest ; extra == 'dev'
Requires-Dist: mkdocs ; extra == 'dev'
Requires-Dist: mkdocs-material >=8.5 ; extra == 'dev'
Requires-Dist: mkdocs-awesome-pages-plugin ; extra == 'dev'
Requires-Dist: mdx-truly-sane-lists ; extra == 'dev'
Requires-Dist: bpython ; extra == 'dev'
Provides-Extra: test
Requires-Dist: freezegun ; extra == 'test'
